smartsheet_pydantic/__init__.py
smartsheet_pydantic/controller.py
smartsheet_pydantic/debug_logger.py
smartsheet_pydantic/filters.py
smartsheet_pydantic/smartmodels.py
smartsheet_pydantic/sources.py
smartsheet_pydantic/transformer.py
smartsheet_pydantic-1.4.5.dist-info/LICENSE
smartsheet_pydantic-1.4.5.dist-info/METADATA
smartsheet_pydantic-1.4.5.dist-info/WHEEL
smartsheet_pydantic-1.4.5.dist-info/top_level.txt
smartsheet_pydantic-1.4.5.dist-info/RECORD
