Metadata-Version: 2.1
Name: smartsheet-pydantic
Version: 1.4.5
Summary: Smartsheet Python SDK and Pydantic Wrapper
Author: Takahiro Watanabe
License: The MIT License (MIT)
Project-URL: Homepage, https://github.com/oneTakeda/smartsheet-pydantic
Keywords: smartsheet,pydantic
Classifier: License :: OSI Approved :: MIT License
Classifier: Programming Language :: Python
Classifier: Programming Language :: Python :: 3
Requires-Python: >=3.10
License-File: LICENSE
Requires-Dist: psycopg2 (>=2.9.6)
Requires-Dist: pydantic (>=1.10.7)
Requires-Dist: requests (>=2.28.2)
Requires-Dist: smartsheet-python-sdk (>=3.0.0)
Provides-Extra: dev
Requires-Dist: coverage ; extra == 'dev'
Requires-Dist: pytest ; extra == 'dev'
